mkyz/__init__.py
mkyz/data_processing.py
mkyz/training.py
mkyz/visualization.py
mkyz/core/__init__.py
mkyz/core/base.py
mkyz/core/config.py
mkyz/core/exceptions.py
mkyz/data/__init__.py
mkyz/data/eda.py
mkyz/data/feature_engineering.py
mkyz/data/loading.py
mkyz/data/preprocessing.py
mkyz/data/validation.py
mkyz/evaluation/__init__.py
mkyz/evaluation/cross_validation.py
mkyz/evaluation/metrics.py
mkyz/evaluation/reports.py
mkyz/persistence/__init__.py
mkyz/persistence/serialization.py
mkyz/utils/__init__.py
mkyz/utils/logging.py
mkyz/utils/parallel.py
mkyz-0.2.3.dist-info/METADATA
mkyz-0.2.3.dist-info/WHEEL
mkyz-0.2.3.dist-info/top_level.txt
mkyz-0.2.3.dist-info/RECORD
