Metadata-Version: 2.4
Name: mkyz
Version: 0.2.3
Summary: MKYZ is a Python library for ML and data science tasks.
Home-page: https://github.com/mmustafakapici/mkyz
Author: Mustafa Kapıcı
Author-email: m.mustafakapici@gmail.com
Classifier: Programming Language :: Python :: 3
Classifier: Operating System :: OS Independent
Requires-Python: >=3.6
Requires-Dist: pandas
Requires-Dist: scikit-learn
Requires-Dist: seaborn
Requires-Dist: matplotlib
Requires-Dist: mlxtend
Requires-Dist: numpy
Requires-Dist: plotly
Requires-Dist: statsmodels
Requires-Dist: xgboost
Requires-Dist: lightgbm
Requires-Dist: catboost
Requires-Dist: rich
Requires-Dist: optuna
Requires-Dist: scipy
Dynamic: author
Dynamic: author-email
Dynamic: classifier
Dynamic: description
Dynamic: description-content-type
Dynamic: home-page
Dynamic: requires-dist
Dynamic: requires-python
Dynamic: summary
